reqsgen/__init__.py
reqsgen/__main__.py
reqsgen/scanner.py
reqsgen/stdlib_modules.py
reqsgen-0.1.0.dist-info/licenses/LICENSE
reqsgen-0.1.0.dist-info/METADATA
reqsgen-0.1.0.dist-info/WHEEL
reqsgen-0.1.0.dist-info/entry_points.txt
reqsgen-0.1.0.dist-info/top_level.txt
reqsgen-0.1.0.dist-info/RECORD
