Metadata-Version: 2.4
Name: reqsgen
Version: 0.1.0
Summary: Generate requirements.txt from your Python imports
Author-email: Ritik Patil <ritik.patil@example.com>
License-Expression: MIT
Project-URL: Homepage, https://github.com/Ritik-Patil/reqsgen
Project-URL: Repository, https://github.com/Ritik-Patil/reqsgen
Project-URL: Issues, https://github.com/Ritik-Patil/reqsgen/issues
Keywords: requirements,dependencies,imports,packaging
Classifier: Development Status :: 4 - Beta
Classifier: Intended Audience :: Developers
Classifier: Programming Language :: Python :: 3
Classifier: Programming Language :: Python :: 3.8
Classifier: Programming Language :: Python :: 3.9
Classifier: Programming Language :: Python :: 3.10
Classifier: Programming Language :: Python :: 3.11
Classifier: Programming Language :: Python :: 3.12
Classifier: Topic :: Software Development :: Libraries :: Python Modules
Classifier: Topic :: System :: Software Distribution
Requires-Python: >=3.8
License-File: LICENSE
Dynamic: license-file
